CHANGES.txt
CONTRIBUTORS.txt
MANIFEST.in
README.txt
setup.py
docs/HISTORY.txt
docs/INSTALL.txt
docs/LICENSE.GPL
docs/LICENSE.txt
src/ityou/__init__.py
src/ityou.esi.theme.egg-info/PKG-INFO
src/ityou.esi.theme.egg-info/SOURCES.txt
src/ityou.esi.theme.egg-info/dependency_links.txt
src/ityou.esi.theme.egg-info/entry_points.txt
src/ityou.esi.theme.egg-info/namespace_packages.txt
src/ityou.esi.theme.egg-info/not-zip-safe
src/ityou.esi.theme.egg-info/requires.txt
src/ityou.esi.theme.egg-info/top_level.txt
src/ityou/esi/__init__.py
src/ityou/esi/theme/__init__.py
src/ityou/esi/theme/config.py
src/ityou/esi/theme/configure.zcml
src/ityou/esi/theme/dbapi.py
src/ityou/esi/theme/interfaces.py
src/ityou/esi/theme/overrides.zcml
src/ityou/esi/theme/skins.zcml
src/ityou/esi/theme/testing.py
src/ityou/esi/theme/testing.zcml
src/ityou/esi/theme/translate.sh
src/ityou/esi/theme/viewlets.py
src/ityou/esi/theme/browser/__init__.py
src/ityou/esi/theme/browser/ajax_notify.py
src/ityou/esi/theme/browser/configure.zcml
src/ityou/esi/theme/browser/controlpanel.py
src/ityou/esi/theme/browser/guide.py
src/ityou/esi/theme/browser/time_test.py
src/ityou/esi/theme/browser/css/esi_theme.css
src/ityou/esi/theme/browser/img/group_icon.png
src/ityou/esi/theme/browser/img/ityou-esi-icon.png
src/ityou/esi/theme/browser/js/theme.js
src/ityou/esi/theme/browser/templates/esi-params.pt
src/ityou/esi/theme/browser/templates/guide.pt
src/ityou/esi/theme/conf/README
src/ityou/esi/theme/controlpanel/__init__.py
src/ityou/esi/theme/controlpanel/control-panel.pt
src/ityou/esi/theme/controlpanel/form.py
src/ityou/esi/theme/controlpanel/memberregistration.pt
src/ityou/esi/theme/controlpanel/overview.pt
src/ityou/esi/theme/controlpanel/overview.py
src/ityou/esi/theme/controlpanel/registration.py
src/ityou/esi/theme/controlpanel/usergroups.py
src/ityou/esi/theme/controlpanel/usergroups_groupdetails.pt
src/ityou/esi/theme/controlpanel/usergroups_groupsoverview.pt
src/ityou/esi/theme/controlpanel/usergroups_usersoverview.pt
src/ityou/esi/theme/controlpanel/usergroupssettings.pt
src/ityou/esi/theme/esi_theme/README.txt
src/ityou/esi/theme/esi_theme/ityou-esi-preview.png
src/ityou/esi/theme/esi_theme/jesi.html
src/ityou/esi/theme/esi_theme/login.html
src/ityou/esi/theme/esi_theme/manifest.cfg
src/ityou/esi/theme/esi_theme/rules-esi.xml
