Metadata-Version: 1.1
Name: ityou.esi.theme
Version: 1.3.1
Summary: ITYOU ESI Theme
Home-page: http://www.ityou.de/esi/
Author: ITYOU/LM
Author-email: lm@ityou.de
License: GPL
Keywords: plone,social,intranet,theme
Platform: UNKNOWN
Classifier: Framework :: Plone
Classifier: Programming Language :: Python
